{
  "schema_version": 1,
  "ref_name": "EmuFpgaXvc",
  "ref_slug": "EmuFpgaXvc",
  "sha": "0beb11a7e3a127e7be5a2e2995bfba5fbefe63c1",
  "short_sha": "0beb11a",
  "run_id": "24428966489",
  "run_url": "https://github.com/slaclab/rogue/actions/runs/24428966489",
  "published_at": "2026-04-15T00:00:51Z",
  "benchmarks": [
    {
      "name": "stream_bridge_perf",
      "complete": true,
      "rx_errors": 0,
      "rate_display": "20.646 MB/s",
      "notes": [
        "frames=10000/10000",
        "elapsed=4.619 s"
      ],
      "primary_metric": {
        "key": "throughput_mb_s",
        "value": 20.64635310793221,
        "unit": "MB/s",
        "better": "higher",
        "display": "20.646 MB/s"
      },
      "raw": {
        "drain_complete": true,
        "elapsed_sec": 4.619093315999976,
        "frame_size": 10000,
        "frames_received": 10000,
        "frames_sent": 10000,
        "name": "stream_bridge_perf",
        "rx_errors": 0,
        "throughput_mb_s": 20.64635310793221,
        "timestamp": 1776211157.8102546
      }
    },
    {
      "name": "udp_packetizer_perf_v1_jumbo",
      "complete": true,
      "rx_errors": 0,
      "rate_display": "18.461 MB/s",
      "notes": [
        "frames=10000/10000",
        "elapsed=5.166 s",
        "ver=1",
        "jumbo=yes"
      ],
      "primary_metric": {
        "key": "throughput_mb_s",
        "value": 18.460979137938413,
        "unit": "MB/s",
        "better": "higher",
        "display": "18.461 MB/s"
      },
      "raw": {
        "drain_complete": true,
        "elapsed_sec": 5.16589239000001,
        "frame_size": 10000,
        "frames_received": 10000,
        "frames_sent": 10000,
        "jumbo": true,
        "name": "udp_packetizer_perf_v1_jumbo",
        "rx_errors": 0,
        "throughput_mb_s": 18.460979137938413,
        "timestamp": 1776211164.064751,
        "version": 1
      }
    },
    {
      "name": "udp_packetizer_perf_v1_std",
      "complete": true,
      "rx_errors": 0,
      "rate_display": "17.390 MB/s",
      "notes": [
        "frames=10000/10000",
        "elapsed=5.484 s",
        "ver=1",
        "jumbo=no"
      ],
      "primary_metric": {
        "key": "throughput_mb_s",
        "value": 17.389835911477665,
        "unit": "MB/s",
        "better": "higher",
        "display": "17.390 MB/s"
      },
      "raw": {
        "drain_complete": true,
        "elapsed_sec": 5.4840903690000005,
        "frame_size": 10000,
        "frames_received": 10000,
        "frames_sent": 10000,
        "jumbo": false,
        "name": "udp_packetizer_perf_v1_std",
        "rx_errors": 0,
        "throughput_mb_s": 17.389835911477665,
        "timestamp": 1776211176.8285875,
        "version": 1
      }
    },
    {
      "name": "udp_packetizer_perf_v2_jumbo",
      "complete": true,
      "rx_errors": 0,
      "rate_display": "18.072 MB/s",
      "notes": [
        "frames=10000/10000",
        "elapsed=5.277 s",
        "ver=2",
        "jumbo=yes"
      ],
      "primary_metric": {
        "key": "throughput_mb_s",
        "value": 18.071540723705635,
        "unit": "MB/s",
        "better": "higher",
        "display": "18.072 MB/s"
      },
      "raw": {
        "drain_complete": true,
        "elapsed_sec": 5.277216430999999,
        "frame_size": 10000,
        "frames_received": 10000,
        "frames_sent": 10000,
        "jumbo": true,
        "name": "udp_packetizer_perf_v2_jumbo",
        "rx_errors": 0,
        "throughput_mb_s": 18.071540723705635,
        "timestamp": 1776211170.3431647,
        "version": 2
      }
    },
    {
      "name": "udp_packetizer_perf_v2_std",
      "complete": true,
      "rx_errors": 0,
      "rate_display": "17.260 MB/s",
      "notes": [
        "frames=10000/10000",
        "elapsed=5.525 s",
        "ver=2",
        "jumbo=no"
      ],
      "primary_metric": {
        "key": "throughput_mb_s",
        "value": 17.260166140239843,
        "unit": "MB/s",
        "better": "higher",
        "display": "17.260 MB/s"
      },
      "raw": {
        "drain_complete": true,
        "elapsed_sec": 5.5252904789999775,
        "frame_size": 10000,
        "frames_received": 10000,
        "frames_sent": 10000,
        "jumbo": false,
        "name": "udp_packetizer_perf_v2_std",
        "rx_errors": 0,
        "throughput_mb_s": 17.260166140239843,
        "timestamp": 1776211183.3550239,
        "version": 2
      }
    },
    {
      "name": "variable_rate_perf_linkedGetRate",
      "complete": true,
      "rx_errors": "n/a",
      "rate_display": "7148.660 ns/op, 139886 ops/s",
      "notes": [
        "cycles=1996935970.000",
        "threshold_pass=yes"
      ],
      "primary_metric": {
        "key": "avg_ns",
        "value": 7148.65972,
        "unit": "ns/op",
        "better": "lower",
        "display": "7148.660 ns/op"
      },
      "raw": {
        "avg_ns": 7148.65972,
        "benchmark": "linkedGetRate",
        "cycles": 1996935970.0,
        "max_avg_ns": 26666.666666666668,
        "max_cycles": 8000000000.0,
        "name": "variable_rate_perf_linkedGetRate",
        "rate_hz": 139886,
        "threshold_pass": true,
        "timestamp": 1776211187.8370416
      }
    },
    {
      "name": "variable_rate_perf_linkedSetRate",
      "complete": true,
      "rx_errors": "n/a",
      "rate_display": "10045.304 ns/op, 99549 ops/s",
      "notes": [
        "cycles=2806091498.000",
        "threshold_pass=yes"
      ],
      "primary_metric": {
        "key": "avg_ns",
        "value": 10045.30421,
        "unit": "ns/op",
        "better": "lower",
        "display": "10045.304 ns/op"
      },
      "raw": {
        "avg_ns": 10045.30421,
        "benchmark": "linkedSetRate",
        "cycles": 2806091498.0,
        "max_avg_ns": 30000.0,
        "max_cycles": 9000000000.0,
        "name": "variable_rate_perf_linkedSetRate",
        "rate_hz": 99549,
        "threshold_pass": true,
        "timestamp": 1776211187.121748
      }
    },
    {
      "name": "variable_rate_perf_localGetRate",
      "complete": true,
      "rx_errors": "n/a",
      "rate_display": "1711.080 ns/op, 584426 ops/s",
      "notes": [
        "cycles=477984048.000",
        "threshold_pass=yes"
      ],
      "primary_metric": {
        "key": "avg_ns",
        "value": 1711.08015,
        "unit": "ns/op",
        "better": "lower",
        "display": "1711.080 ns/op"
      },
      "raw": {
        "avg_ns": 1711.08015,
        "benchmark": "localGetRate",
        "cycles": 477984048.0,
        "max_avg_ns": 20000.0,
        "max_cycles": 6000000000.0,
        "name": "variable_rate_perf_localGetRate",
        "rate_hz": 584426,
        "threshold_pass": true,
        "timestamp": 1776211186.116909
      }
    },
    {
      "name": "variable_rate_perf_localSetRate",
      "complete": true,
      "rx_errors": "n/a",
      "rate_display": "2322.888 ns/op, 430498 ops/s",
      "notes": [
        "cycles=648890330.000",
        "threshold_pass=yes"
      ],
      "primary_metric": {
        "key": "avg_ns",
        "value": 2322.88776,
        "unit": "ns/op",
        "better": "lower",
        "display": "2322.888 ns/op"
      },
      "raw": {
        "avg_ns": 2322.88776,
        "benchmark": "localSetRate",
        "cycles": 648890330.0,
        "max_avg_ns": 26666.666666666668,
        "max_cycles": 8000000000.0,
        "name": "variable_rate_perf_localSetRate",
        "rate_hz": 430498,
        "threshold_pass": true,
        "timestamp": 1776211185.9454684
      }
    },
    {
      "name": "variable_rate_perf_remoteGetRate",
      "complete": true,
      "rx_errors": "n/a",
      "rate_display": "6422.115 ns/op, 155711 ops/s",
      "notes": [
        "cycles=1793980822.000",
        "threshold_pass=yes"
      ],
      "primary_metric": {
        "key": "avg_ns",
        "value": 6422.11499,
        "unit": "ns/op",
        "better": "lower",
        "display": "6422.115 ns/op"
      },
      "raw": {
        "avg_ns": 6422.11499,
        "benchmark": "remoteGetRate",
        "cycles": 1793980822.0,
        "max_avg_ns": 20000.0,
        "max_cycles": 6000000000.0,
        "name": "variable_rate_perf_remoteGetRate",
        "rate_hz": 155711,
        "threshold_pass": true,
        "timestamp": 1776211185.7128158
      }
    },
    {
      "name": "variable_rate_perf_remoteSetNvRate",
      "complete": true,
      "rx_errors": "n/a",
      "rate_display": "7628.008 ns/op, 131095 ops/s",
      "notes": [
        "cycles=2130843301.000",
        "threshold_pass=yes"
      ],
      "primary_metric": {
        "key": "avg_ns",
        "value": 7628.00797,
        "unit": "ns/op",
        "better": "lower",
        "display": "7628.008 ns/op"
      },
      "raw": {
        "avg_ns": 7628.00797,
        "benchmark": "remoteSetNvRate",
        "cycles": 2130843301.0,
        "max_avg_ns": 23333.333333333332,
        "max_cycles": 7000000000.0,
        "name": "variable_rate_perf_remoteSetNvRate",
        "rate_hz": 131095,
        "threshold_pass": true,
        "timestamp": 1776211185.0702436
      }
    },
    {
      "name": "variable_rate_perf_remoteSetRate",
      "complete": true,
      "rx_errors": "n/a",
      "rate_display": "9429.287 ns/op, 106052 ops/s",
      "notes": [
        "cycles=2634007098.000",
        "threshold_pass=yes"
      ],
      "primary_metric": {
        "key": "avg_ns",
        "value": 9429.28656,
        "unit": "ns/op",
        "better": "lower",
        "display": "9429.287 ns/op"
      },
      "raw": {
        "avg_ns": 9429.28656,
        "benchmark": "remoteSetRate",
        "cycles": 2634007098.0,
        "max_avg_ns": 26666.666666666668,
        "max_cycles": 8000000000.0,
        "name": "variable_rate_perf_remoteSetRate",
        "rate_hz": 106052,
        "threshold_pass": true,
        "timestamp": 1776211184.3070147
      }
    }
  ]
}
