{
  "schema_version": 1,
  "ref_name": "improve-thread-safety-and-memory-lifetime",
  "ref_slug": "improve-thread-safety-and-memory-lifetime",
  "sha": "a693383f9fc06d474dbebdeabc3b7bff6f6a5fae",
  "short_sha": "a693383",
  "run_id": "24919575143",
  "run_url": "https://github.com/slaclab/rogue/actions/runs/24919575143",
  "published_at": "2026-04-25T01:46:22Z",
  "benchmarks": [
    {
      "name": "fifo_perf",
      "complete": true,
      "rx_errors": 0,
      "rate_display": "32.229 MB/s",
      "notes": [
        "frames=10000/10000",
        "elapsed=2.959 s"
      ],
      "primary_metric": {
        "key": "throughput_mb_s",
        "value": 32.229316479066384,
        "unit": "MB/s",
        "better": "higher",
        "display": "32.229 MB/s"
      },
      "raw": {
        "drain_complete": true,
        "elapsed_sec": 2.959027433999978,
        "frame_size": 10000,
        "frames_received": 10000,
        "frames_sent": 10000,
        "name": "fifo_perf",
        "rx_errors": 0,
        "throughput_mb_s": 32.229316479066384,
        "timestamp": 1777081512.920511
      }
    },
    {
      "name": "stream_bridge_perf",
      "complete": true,
      "rx_errors": 0,
      "rate_display": "32.115 MB/s",
      "notes": [
        "frames=10000/10000",
        "elapsed=2.970 s"
      ],
      "primary_metric": {
        "key": "throughput_mb_s",
        "value": 32.11494854520688,
        "unit": "MB/s",
        "better": "higher",
        "display": "32.115 MB/s"
      },
      "raw": {
        "drain_complete": true,
        "elapsed_sec": 2.9695651389999966,
        "frame_size": 10000,
        "frames_received": 10000,
        "frames_sent": 10000,
        "name": "stream_bridge_perf",
        "rx_errors": 0,
        "throughput_mb_s": 32.11494854520688,
        "timestamp": 1777081515.893217
      }
    },
    {
      "name": "udp_packetizer_perf_v1_jumbo",
      "complete": true,
      "rx_errors": 0,
      "rate_display": "27.216 MB/s",
      "notes": [
        "frames=10000/10000",
        "elapsed=3.504 s",
        "ver=1",
        "jumbo=yes"
      ],
      "primary_metric": {
        "key": "throughput_mb_s",
        "value": 27.215906215273286,
        "unit": "MB/s",
        "better": "higher",
        "display": "27.216 MB/s"
      },
      "raw": {
        "drain_complete": true,
        "elapsed_sec": 3.504106417999992,
        "frame_size": 10000,
        "frames_received": 10000,
        "frames_sent": 10000,
        "jumbo": true,
        "name": "udp_packetizer_perf_v1_jumbo",
        "rx_errors": 0,
        "throughput_mb_s": 27.215906215273286,
        "timestamp": 1777081520.4337282,
        "version": 1
      }
    },
    {
      "name": "udp_packetizer_perf_v1_std",
      "complete": true,
      "rx_errors": 0,
      "rate_display": "22.136 MB/s",
      "notes": [
        "frames=10000/10000",
        "elapsed=4.308 s",
        "ver=1",
        "jumbo=no"
      ],
      "primary_metric": {
        "key": "throughput_mb_s",
        "value": 22.136257622276933,
        "unit": "MB/s",
        "better": "higher",
        "display": "22.136 MB/s"
      },
      "raw": {
        "drain_complete": true,
        "elapsed_sec": 4.308200295999967,
        "frame_size": 10000,
        "frames_received": 10000,
        "frames_sent": 10000,
        "jumbo": false,
        "name": "udp_packetizer_perf_v1_std",
        "rx_errors": 0,
        "throughput_mb_s": 22.136257622276933,
        "timestamp": 1777081530.2654526,
        "version": 1
      }
    },
    {
      "name": "udp_packetizer_perf_v2_jumbo",
      "complete": true,
      "rx_errors": 0,
      "rate_display": "27.086 MB/s",
      "notes": [
        "frames=10000/10000",
        "elapsed=3.521 s",
        "ver=2",
        "jumbo=yes"
      ],
      "primary_metric": {
        "key": "throughput_mb_s",
        "value": 27.085786100639627,
        "unit": "MB/s",
        "better": "higher",
        "display": "27.086 MB/s"
      },
      "raw": {
        "drain_complete": true,
        "elapsed_sec": 3.5209401449999973,
        "frame_size": 10000,
        "frames_received": 10000,
        "frames_sent": 10000,
        "jumbo": true,
        "name": "udp_packetizer_perf_v2_jumbo",
        "rx_errors": 0,
        "throughput_mb_s": 27.085786100639627,
        "timestamp": 1777081524.9559574,
        "version": 2
      }
    },
    {
      "name": "udp_packetizer_perf_v2_std",
      "complete": true,
      "rx_errors": 0,
      "rate_display": "22.082 MB/s",
      "notes": [
        "frames=10000/10000",
        "elapsed=4.319 s",
        "ver=2",
        "jumbo=no"
      ],
      "primary_metric": {
        "key": "throughput_mb_s",
        "value": 22.081964696026013,
        "unit": "MB/s",
        "better": "higher",
        "display": "22.082 MB/s"
      },
      "raw": {
        "drain_complete": true,
        "elapsed_sec": 4.318792868000003,
        "frame_size": 10000,
        "frames_received": 10000,
        "frames_sent": 10000,
        "jumbo": false,
        "name": "udp_packetizer_perf_v2_std",
        "rx_errors": 0,
        "throughput_mb_s": 22.081964696026013,
        "timestamp": 1777081535.585817,
        "version": 2
      }
    },
    {
      "name": "variable_rate_perf_linkedGetRate",
      "complete": true,
      "rx_errors": "n/a",
      "rate_display": "8575.641 ns/op, 116609 ops/s",
      "notes": [
        "cycles=2097133189.000",
        "threshold_pass=yes"
      ],
      "primary_metric": {
        "key": "avg_ns",
        "value": 8575.64066,
        "unit": "ns/op",
        "better": "lower",
        "display": "8575.641 ns/op"
      },
      "raw": {
        "avg_ns": 8575.64066,
        "benchmark": "linkedGetRate",
        "cycles": 2097133189.0,
        "max_avg_ns": 26666.666666666668,
        "max_cycles": 8000000000.0,
        "name": "variable_rate_perf_linkedGetRate",
        "rate_hz": 116609,
        "threshold_pass": true,
        "timestamp": 1777081541.0360014
      }
    },
    {
      "name": "variable_rate_perf_linkedSetRate",
      "complete": true,
      "rx_errors": "n/a",
      "rate_display": "12255.936 ns/op, 81593 ops/s",
      "notes": [
        "cycles=2997129369.000",
        "threshold_pass=yes"
      ],
      "primary_metric": {
        "key": "avg_ns",
        "value": 12255.93596,
        "unit": "ns/op",
        "better": "lower",
        "display": "12255.936 ns/op"
      },
      "raw": {
        "avg_ns": 12255.93596,
        "benchmark": "linkedSetRate",
        "cycles": 2997129369.0,
        "max_avg_ns": 30000.0,
        "max_cycles": 9000000000.0,
        "name": "variable_rate_perf_linkedSetRate",
        "rate_hz": 81593,
        "threshold_pass": true,
        "timestamp": 1777081540.1780164
      }
    },
    {
      "name": "variable_rate_perf_localGetRate",
      "complete": true,
      "rx_errors": "n/a",
      "rate_display": "1828.216 ns/op, 546981 ops/s",
      "notes": [
        "cycles=447077862.000",
        "threshold_pass=yes"
      ],
      "primary_metric": {
        "key": "avg_ns",
        "value": 1828.21623,
        "unit": "ns/op",
        "better": "lower",
        "display": "1828.216 ns/op"
      },
      "raw": {
        "avg_ns": 1828.21623,
        "benchmark": "localGetRate",
        "cycles": 447077862.0,
        "max_avg_ns": 20000.0,
        "max_cycles": 6000000000.0,
        "name": "variable_rate_perf_localGetRate",
        "rate_hz": 546981,
        "threshold_pass": true,
        "timestamp": 1777081538.9509044
      }
    },
    {
      "name": "variable_rate_perf_localSetRate",
      "complete": true,
      "rx_errors": "n/a",
      "rate_display": "2486.103 ns/op, 402235 ops/s",
      "notes": [
        "cycles=607963555.000",
        "threshold_pass=yes"
      ],
      "primary_metric": {
        "key": "avg_ns",
        "value": 2486.10327,
        "unit": "ns/op",
        "better": "lower",
        "display": "2486.103 ns/op"
      },
      "raw": {
        "avg_ns": 2486.10327,
        "benchmark": "localSetRate",
        "cycles": 607963555.0,
        "max_avg_ns": 26666.666666666668,
        "max_cycles": 8000000000.0,
        "name": "variable_rate_perf_localSetRate",
        "rate_hz": 402235,
        "threshold_pass": true,
        "timestamp": 1777081538.767752
      }
    },
    {
      "name": "variable_rate_perf_remoteGetRate",
      "complete": true,
      "rx_errors": "n/a",
      "rate_display": "7825.257 ns/op, 127791 ops/s",
      "notes": [
        "cycles=1913629315.000",
        "threshold_pass=yes"
      ],
      "primary_metric": {
        "key": "avg_ns",
        "value": 7825.25703,
        "unit": "ns/op",
        "better": "lower",
        "display": "7825.257 ns/op"
      },
      "raw": {
        "avg_ns": 7825.25703,
        "benchmark": "remoteGetRate",
        "cycles": 1913629315.0,
        "max_avg_ns": 20000.0,
        "max_cycles": 6000000000.0,
        "name": "variable_rate_perf_remoteGetRate",
        "rate_hz": 127791,
        "threshold_pass": true,
        "timestamp": 1777081538.5187323
      }
    },
    {
      "name": "variable_rate_perf_remoteSetNvRate",
      "complete": true,
      "rx_errors": "n/a",
      "rate_display": "9639.099 ns/op, 103744 ops/s",
      "notes": [
        "cycles=2357196940.000",
        "threshold_pass=yes"
      ],
      "primary_metric": {
        "key": "avg_ns",
        "value": 9639.09944,
        "unit": "ns/op",
        "better": "lower",
        "display": "9639.099 ns/op"
      },
      "raw": {
        "avg_ns": 9639.09944,
        "benchmark": "remoteSetNvRate",
        "cycles": 2357196940.0,
        "max_avg_ns": 23333.333333333332,
        "max_cycles": 7000000000.0,
        "name": "variable_rate_perf_remoteSetNvRate",
        "rate_hz": 103744,
        "threshold_pass": true,
        "timestamp": 1777081537.7357855
      }
    },
    {
      "name": "variable_rate_perf_remoteSetRate",
      "complete": true,
      "rx_errors": "n/a",
      "rate_display": "11751.756 ns/op, 85093 ops/s",
      "notes": [
        "cycles=2873831543.000",
        "threshold_pass=yes"
      ],
      "primary_metric": {
        "key": "avg_ns",
        "value": 11751.75575,
        "unit": "ns/op",
        "better": "lower",
        "display": "11751.756 ns/op"
      },
      "raw": {
        "avg_ns": 11751.75575,
        "benchmark": "remoteSetRate",
        "cycles": 2873831543.0,
        "max_avg_ns": 26666.666666666668,
        "max_cycles": 8000000000.0,
        "name": "variable_rate_perf_remoteSetRate",
        "rate_hz": 85093,
        "threshold_pass": true,
        "timestamp": 1777081536.7714288
      }
    }
  ]
}
