{
  "schema_version": 1,
  "ref_name": "hunt-for-red-october",
  "ref_slug": "hunt-for-red-october",
  "sha": "28604f1378a06b106464cf60a493e23c4da1664f",
  "short_sha": "28604f1",
  "run_id": "24889948516",
  "run_url": "https://github.com/slaclab/rogue/actions/runs/24889948516",
  "published_at": "2026-04-24T12:43:12Z",
  "benchmarks": [
    {
      "name": "fifo_perf",
      "complete": true,
      "rx_errors": 0,
      "rate_display": "27.993 MB/s",
      "notes": [
        "frames=10000/10000",
        "elapsed=3.407 s"
      ],
      "primary_metric": {
        "key": "throughput_mb_s",
        "value": 27.992768481719374,
        "unit": "MB/s",
        "better": "higher",
        "display": "27.993 MB/s"
      },
      "raw": {
        "drain_complete": true,
        "elapsed_sec": 3.4068595860000244,
        "frame_size": 10000,
        "frames_received": 10000,
        "frames_sent": 10000,
        "name": "fifo_perf",
        "rx_errors": 0,
        "throughput_mb_s": 27.992768481719374,
        "timestamp": 1777034512.2489722
      }
    },
    {
      "name": "stream_bridge_perf",
      "complete": true,
      "rx_errors": 0,
      "rate_display": "27.723 MB/s",
      "notes": [
        "frames=10000/10000",
        "elapsed=3.440 s"
      ],
      "primary_metric": {
        "key": "throughput_mb_s",
        "value": 27.723448749538065,
        "unit": "MB/s",
        "better": "higher",
        "display": "27.723 MB/s"
      },
      "raw": {
        "drain_complete": true,
        "elapsed_sec": 3.4399555589999977,
        "frame_size": 10000,
        "frames_received": 10000,
        "frames_sent": 10000,
        "name": "stream_bridge_perf",
        "rx_errors": 0,
        "throughput_mb_s": 27.723448749538065,
        "timestamp": 1777034515.692221
      }
    },
    {
      "name": "udp_packetizer_perf_v1_jumbo",
      "complete": true,
      "rx_errors": 0,
      "rate_display": "24.757 MB/s",
      "notes": [
        "frames=10000/10000",
        "elapsed=3.852 s",
        "ver=1",
        "jumbo=yes"
      ],
      "primary_metric": {
        "key": "throughput_mb_s",
        "value": 24.756589950642383,
        "unit": "MB/s",
        "better": "higher",
        "display": "24.757 MB/s"
      },
      "raw": {
        "drain_complete": true,
        "elapsed_sec": 3.852203871000029,
        "frame_size": 10000,
        "frames_received": 10000,
        "frames_sent": 10000,
        "jumbo": true,
        "name": "udp_packetizer_perf_v1_jumbo",
        "rx_errors": 0,
        "throughput_mb_s": 24.756589950642383,
        "timestamp": 1777034520.6117737,
        "version": 1
      }
    },
    {
      "name": "udp_packetizer_perf_v1_std",
      "complete": true,
      "rx_errors": 0,
      "rate_display": "23.306 MB/s",
      "notes": [
        "frames=10000/10000",
        "elapsed=4.092 s",
        "ver=1",
        "jumbo=no"
      ],
      "primary_metric": {
        "key": "throughput_mb_s",
        "value": 23.305982180061072,
        "unit": "MB/s",
        "better": "higher",
        "display": "23.306 MB/s"
      },
      "raw": {
        "drain_complete": true,
        "elapsed_sec": 4.091972220000002,
        "frame_size": 10000,
        "frames_received": 10000,
        "frames_sent": 10000,
        "jumbo": false,
        "name": "udp_packetizer_perf_v1_std",
        "rx_errors": 0,
        "throughput_mb_s": 23.305982180061072,
        "timestamp": 1777034530.5865927,
        "version": 1
      }
    },
    {
      "name": "udp_packetizer_perf_v2_jumbo",
      "complete": true,
      "rx_errors": 0,
      "rate_display": "24.579 MB/s",
      "notes": [
        "frames=10000/10000",
        "elapsed=3.880 s",
        "ver=2",
        "jumbo=yes"
      ],
      "primary_metric": {
        "key": "throughput_mb_s",
        "value": 24.578945510166623,
        "unit": "MB/s",
        "better": "higher",
        "display": "24.579 MB/s"
      },
      "raw": {
        "drain_complete": true,
        "elapsed_sec": 3.88004569200001,
        "frame_size": 10000,
        "frames_received": 10000,
        "frames_sent": 10000,
        "jumbo": true,
        "name": "udp_packetizer_perf_v2_jumbo",
        "rx_errors": 0,
        "throughput_mb_s": 24.578945510166623,
        "timestamp": 1777034525.4931943,
        "version": 2
      }
    },
    {
      "name": "udp_packetizer_perf_v2_std",
      "complete": true,
      "rx_errors": 0,
      "rate_display": "23.224 MB/s",
      "notes": [
        "frames=10000/10000",
        "elapsed=4.106 s",
        "ver=2",
        "jumbo=no"
      ],
      "primary_metric": {
        "key": "throughput_mb_s",
        "value": 23.22385337087371,
        "unit": "MB/s",
        "better": "higher",
        "display": "23.224 MB/s"
      },
      "raw": {
        "drain_complete": true,
        "elapsed_sec": 4.106443065999997,
        "frame_size": 10000,
        "frames_received": 10000,
        "frames_sent": 10000,
        "jumbo": false,
        "name": "udp_packetizer_perf_v2_std",
        "rx_errors": 0,
        "throughput_mb_s": 23.22385337087371,
        "timestamp": 1777034535.6943004,
        "version": 2
      }
    },
    {
      "name": "variable_rate_perf_linkedGetRate",
      "complete": true,
      "rx_errors": "n/a",
      "rate_display": "7061.589 ns/op, 141611 ops/s",
      "notes": [
        "cycles=1833264134.000",
        "threshold_pass=yes"
      ],
      "primary_metric": {
        "key": "avg_ns",
        "value": 7061.58937,
        "unit": "ns/op",
        "better": "lower",
        "display": "7061.589 ns/op"
      },
      "raw": {
        "avg_ns": 7061.58937,
        "benchmark": "linkedGetRate",
        "cycles": 1833264134.0,
        "max_avg_ns": 26666.666666666668,
        "max_cycles": 8000000000.0,
        "name": "variable_rate_perf_linkedGetRate",
        "rate_hz": 141611,
        "threshold_pass": true,
        "timestamp": 1777034540.1261811
      }
    },
    {
      "name": "variable_rate_perf_linkedSetRate",
      "complete": true,
      "rx_errors": "n/a",
      "rate_display": "9889.356 ns/op, 101118 ops/s",
      "notes": [
        "cycles=2567375616.000",
        "threshold_pass=yes"
      ],
      "primary_metric": {
        "key": "avg_ns",
        "value": 9889.35611,
        "unit": "ns/op",
        "better": "lower",
        "display": "9889.356 ns/op"
      },
      "raw": {
        "avg_ns": 9889.35611,
        "benchmark": "linkedSetRate",
        "cycles": 2567375616.0,
        "max_avg_ns": 30000.0,
        "max_cycles": 9000000000.0,
        "name": "variable_rate_perf_linkedSetRate",
        "rate_hz": 101118,
        "threshold_pass": true,
        "timestamp": 1777034539.4195466
      }
    },
    {
      "name": "variable_rate_perf_localGetRate",
      "complete": true,
      "rx_errors": "n/a",
      "rate_display": "1719.004 ns/op, 581732 ops/s",
      "notes": [
        "cycles=446280848.000",
        "threshold_pass=yes"
      ],
      "primary_metric": {
        "key": "avg_ns",
        "value": 1719.00446,
        "unit": "ns/op",
        "better": "lower",
        "display": "1719.004 ns/op"
      },
      "raw": {
        "avg_ns": 1719.00446,
        "benchmark": "localGetRate",
        "cycles": 446280848.0,
        "max_avg_ns": 20000.0,
        "max_cycles": 6000000000.0,
        "name": "variable_rate_perf_localGetRate",
        "rate_hz": 581732,
        "threshold_pass": true,
        "timestamp": 1777034538.428789
      }
    },
    {
      "name": "variable_rate_perf_localSetRate",
      "complete": true,
      "rx_errors": "n/a",
      "rate_display": "2392.501 ns/op, 417972 ops/s",
      "notes": [
        "cycles=621130614.000",
        "threshold_pass=yes"
      ],
      "primary_metric": {
        "key": "avg_ns",
        "value": 2392.50112,
        "unit": "ns/op",
        "better": "lower",
        "display": "2392.501 ns/op"
      },
      "raw": {
        "avg_ns": 2392.50112,
        "benchmark": "localSetRate",
        "cycles": 621130614.0,
        "max_avg_ns": 26666.666666666668,
        "max_cycles": 8000000000.0,
        "name": "variable_rate_perf_localSetRate",
        "rate_hz": 417972,
        "threshold_pass": true,
        "timestamp": 1777034538.2564495
      }
    },
    {
      "name": "variable_rate_perf_remoteGetRate",
      "complete": true,
      "rx_errors": "n/a",
      "rate_display": "6253.729 ns/op, 159904 ops/s",
      "notes": [
        "cycles=1623537722.000",
        "threshold_pass=yes"
      ],
      "primary_metric": {
        "key": "avg_ns",
        "value": 6253.72867,
        "unit": "ns/op",
        "better": "lower",
        "display": "6253.729 ns/op"
      },
      "raw": {
        "avg_ns": 6253.72867,
        "benchmark": "remoteGetRate",
        "cycles": 1623537722.0,
        "max_avg_ns": 20000.0,
        "max_cycles": 6000000000.0,
        "name": "variable_rate_perf_remoteGetRate",
        "rate_hz": 159904,
        "threshold_pass": true,
        "timestamp": 1777034538.0167344
      }
    },
    {
      "name": "variable_rate_perf_remoteSetNvRate",
      "complete": true,
      "rx_errors": "n/a",
      "rate_display": "7510.802 ns/op, 133141 ops/s",
      "notes": [
        "cycles=1949883962.000",
        "threshold_pass=yes"
      ],
      "primary_metric": {
        "key": "avg_ns",
        "value": 7510.80174,
        "unit": "ns/op",
        "better": "lower",
        "display": "7510.802 ns/op"
      },
      "raw": {
        "avg_ns": 7510.80174,
        "benchmark": "remoteSetNvRate",
        "cycles": 1949883962.0,
        "max_avg_ns": 23333.333333333332,
        "max_cycles": 7000000000.0,
        "name": "variable_rate_perf_remoteSetNvRate",
        "rate_hz": 133141,
        "threshold_pass": true,
        "timestamp": 1777034537.390872
      }
    },
    {
      "name": "variable_rate_perf_remoteSetRate",
      "complete": true,
      "rx_errors": "n/a",
      "rate_display": "9358.635 ns/op, 106853 ops/s",
      "notes": [
        "cycles=2429597794.000",
        "threshold_pass=yes"
      ],
      "primary_metric": {
        "key": "avg_ns",
        "value": 9358.63524,
        "unit": "ns/op",
        "better": "lower",
        "display": "9358.635 ns/op"
      },
      "raw": {
        "avg_ns": 9358.63524,
        "benchmark": "remoteSetRate",
        "cycles": 2429597794.0,
        "max_avg_ns": 26666.666666666668,
        "max_cycles": 8000000000.0,
        "name": "variable_rate_perf_remoteSetRate",
        "rate_hz": 106853,
        "threshold_pass": true,
        "timestamp": 1777034536.6392868
      }
    }
  ]
}
