{
  "schema_version": 1,
  "ref_name": "hunt-for-red-october",
  "ref_slug": "hunt-for-red-october",
  "sha": "bb297955f38a4266c432ca672dca98822063c9d9",
  "short_sha": "bb29795",
  "run_id": "24874399269",
  "run_url": "https://github.com/slaclab/rogue/actions/runs/24874399269",
  "published_at": "2026-04-24T05:51:19Z",
  "benchmarks": [
    {
      "name": "fifo_perf",
      "complete": true,
      "rx_errors": 0,
      "rate_display": "32.104 MB/s",
      "notes": [
        "frames=10000/10000",
        "elapsed=2.971 s"
      ],
      "primary_metric": {
        "key": "throughput_mb_s",
        "value": 32.10361987546074,
        "unit": "MB/s",
        "better": "higher",
        "display": "32.104 MB/s"
      },
      "raw": {
        "drain_complete": true,
        "elapsed_sec": 2.970613033999996,
        "frame_size": 10000,
        "frames_received": 10000,
        "frames_sent": 10000,
        "name": "fifo_perf",
        "rx_errors": 0,
        "throughput_mb_s": 32.10361987546074,
        "timestamp": 1777009792.7483592
      }
    },
    {
      "name": "stream_bridge_perf",
      "complete": true,
      "rx_errors": 0,
      "rate_display": "32.322 MB/s",
      "notes": [
        "frames=10000/10000",
        "elapsed=2.951 s"
      ],
      "primary_metric": {
        "key": "throughput_mb_s",
        "value": 32.32159054222836,
        "unit": "MB/s",
        "better": "higher",
        "display": "32.322 MB/s"
      },
      "raw": {
        "drain_complete": true,
        "elapsed_sec": 2.9505797840000128,
        "frame_size": 10000,
        "frames_received": 10000,
        "frames_sent": 10000,
        "name": "stream_bridge_perf",
        "rx_errors": 0,
        "throughput_mb_s": 32.32159054222836,
        "timestamp": 1777009795.7021716
      }
    },
    {
      "name": "udp_packetizer_perf_v1_jumbo",
      "complete": true,
      "rx_errors": 0,
      "rate_display": "27.069 MB/s",
      "notes": [
        "frames=10000/10000",
        "elapsed=3.523 s",
        "ver=1",
        "jumbo=yes"
      ],
      "primary_metric": {
        "key": "throughput_mb_s",
        "value": 27.068595981488965,
        "unit": "MB/s",
        "better": "higher",
        "display": "27.069 MB/s"
      },
      "raw": {
        "drain_complete": true,
        "elapsed_sec": 3.523176145000008,
        "frame_size": 10000,
        "frames_received": 10000,
        "frames_sent": 10000,
        "jumbo": true,
        "name": "udp_packetizer_perf_v1_jumbo",
        "rx_errors": 0,
        "throughput_mb_s": 27.068595981488965,
        "timestamp": 1777009800.281032,
        "version": 1
      }
    },
    {
      "name": "udp_packetizer_perf_v1_std",
      "complete": true,
      "rx_errors": 0,
      "rate_display": "22.291 MB/s",
      "notes": [
        "frames=10000/10000",
        "elapsed=4.278 s",
        "ver=1",
        "jumbo=no"
      ],
      "primary_metric": {
        "key": "throughput_mb_s",
        "value": 22.291273091919205,
        "unit": "MB/s",
        "better": "higher",
        "display": "22.291 MB/s"
      },
      "raw": {
        "drain_complete": true,
        "elapsed_sec": 4.278240693000015,
        "frame_size": 10000,
        "frames_received": 10000,
        "frames_sent": 10000,
        "jumbo": false,
        "name": "udp_packetizer_perf_v1_std",
        "rx_errors": 0,
        "throughput_mb_s": 22.291273091919205,
        "timestamp": 1777009810.1306534,
        "version": 1
      }
    },
    {
      "name": "udp_packetizer_perf_v2_jumbo",
      "complete": true,
      "rx_errors": 0,
      "rate_display": "26.725 MB/s",
      "notes": [
        "frames=10000/10000",
        "elapsed=3.568 s",
        "ver=2",
        "jumbo=yes"
      ],
      "primary_metric": {
        "key": "throughput_mb_s",
        "value": 26.724904315316238,
        "unit": "MB/s",
        "better": "higher",
        "display": "26.725 MB/s"
      },
      "raw": {
        "drain_complete": true,
        "elapsed_sec": 3.568485428999992,
        "frame_size": 10000,
        "frames_received": 10000,
        "frames_sent": 10000,
        "jumbo": true,
        "name": "udp_packetizer_perf_v2_jumbo",
        "rx_errors": 0,
        "throughput_mb_s": 26.724904315316238,
        "timestamp": 1777009804.8509414,
        "version": 2
      }
    },
    {
      "name": "udp_packetizer_perf_v2_std",
      "complete": true,
      "rx_errors": 0,
      "rate_display": "21.886 MB/s",
      "notes": [
        "frames=10000/10000",
        "elapsed=4.358 s",
        "ver=2",
        "jumbo=no"
      ],
      "primary_metric": {
        "key": "throughput_mb_s",
        "value": 21.885597389694436,
        "unit": "MB/s",
        "better": "higher",
        "display": "21.886 MB/s"
      },
      "raw": {
        "drain_complete": true,
        "elapsed_sec": 4.357542997000024,
        "frame_size": 10000,
        "frames_received": 10000,
        "frames_sent": 10000,
        "jumbo": false,
        "name": "udp_packetizer_perf_v2_std",
        "rx_errors": 0,
        "throughput_mb_s": 21.885597389694436,
        "timestamp": 1777009815.4897046,
        "version": 2
      }
    },
    {
      "name": "variable_rate_perf_linkedGetRate",
      "complete": true,
      "rx_errors": "n/a",
      "rate_display": "7118.279 ns/op, 140483 ops/s",
      "notes": [
        "cycles=1740727010.000",
        "threshold_pass=yes"
      ],
      "primary_metric": {
        "key": "avg_ns",
        "value": 7118.27932,
        "unit": "ns/op",
        "better": "lower",
        "display": "7118.279 ns/op"
      },
      "raw": {
        "avg_ns": 7118.27932,
        "benchmark": "linkedGetRate",
        "cycles": 1740727010.0,
        "max_avg_ns": 26666.666666666668,
        "max_cycles": 8000000000.0,
        "name": "variable_rate_perf_linkedGetRate",
        "rate_hz": 140483,
        "threshold_pass": true,
        "timestamp": 1777009820.060361
      }
    },
    {
      "name": "variable_rate_perf_linkedSetRate",
      "complete": true,
      "rx_errors": "n/a",
      "rate_display": "10137.416 ns/op, 98644 ops/s",
      "notes": [
        "cycles=2479028723.000",
        "threshold_pass=yes"
      ],
      "primary_metric": {
        "key": "avg_ns",
        "value": 10137.41587,
        "unit": "ns/op",
        "better": "lower",
        "display": "10137.416 ns/op"
      },
      "raw": {
        "avg_ns": 10137.41587,
        "benchmark": "linkedSetRate",
        "cycles": 2479028723.0,
        "max_avg_ns": 30000.0,
        "max_cycles": 9000000000.0,
        "name": "variable_rate_perf_linkedSetRate",
        "rate_hz": 98644,
        "threshold_pass": true,
        "timestamp": 1777009819.348073
      }
    },
    {
      "name": "variable_rate_perf_localGetRate",
      "complete": true,
      "rx_errors": "n/a",
      "rate_display": "1800.381 ns/op, 555437 ops/s",
      "notes": [
        "cycles=440281317.000",
        "threshold_pass=yes"
      ],
      "primary_metric": {
        "key": "avg_ns",
        "value": 1800.38126,
        "unit": "ns/op",
        "better": "lower",
        "display": "1800.381 ns/op"
      },
      "raw": {
        "avg_ns": 1800.38126,
        "benchmark": "localGetRate",
        "cycles": 440281317.0,
        "max_avg_ns": 20000.0,
        "max_cycles": 6000000000.0,
        "name": "variable_rate_perf_localGetRate",
        "rate_hz": 555437,
        "threshold_pass": true,
        "timestamp": 1777009818.3323653
      }
    },
    {
      "name": "variable_rate_perf_localSetRate",
      "complete": true,
      "rx_errors": "n/a",
      "rate_display": "2512.555 ns/op, 398001 ops/s",
      "notes": [
        "cycles=614433344.000",
        "threshold_pass=yes"
      ],
      "primary_metric": {
        "key": "avg_ns",
        "value": 2512.5552,
        "unit": "ns/op",
        "better": "lower",
        "display": "2512.555 ns/op"
      },
      "raw": {
        "avg_ns": 2512.5552,
        "benchmark": "localSetRate",
        "cycles": 614433344.0,
        "max_avg_ns": 26666.666666666668,
        "max_cycles": 8000000000.0,
        "name": "variable_rate_perf_localSetRate",
        "rate_hz": 398001,
        "threshold_pass": true,
        "timestamp": 1777009818.151862
      }
    },
    {
      "name": "variable_rate_perf_remoteGetRate",
      "complete": true,
      "rx_errors": "n/a",
      "rate_display": "6450.594 ns/op, 155024 ops/s",
      "notes": [
        "cycles=1577450291.000",
        "threshold_pass=yes"
      ],
      "primary_metric": {
        "key": "avg_ns",
        "value": 6450.5943,
        "unit": "ns/op",
        "better": "lower",
        "display": "6450.594 ns/op"
      },
      "raw": {
        "avg_ns": 6450.5943,
        "benchmark": "remoteGetRate",
        "cycles": 1577450291.0,
        "max_avg_ns": 20000.0,
        "max_cycles": 6000000000.0,
        "name": "variable_rate_perf_remoteGetRate",
        "rate_hz": 155024,
        "threshold_pass": true,
        "timestamp": 1777009817.900086
      }
    },
    {
      "name": "variable_rate_perf_remoteSetNvRate",
      "complete": true,
      "rx_errors": "n/a",
      "rate_display": "8123.222 ns/op, 123103 ops/s",
      "notes": [
        "cycles=1986477641.000",
        "threshold_pass=yes"
      ],
      "primary_metric": {
        "key": "avg_ns",
        "value": 8123.2222,
        "unit": "ns/op",
        "better": "lower",
        "display": "8123.222 ns/op"
      },
      "raw": {
        "avg_ns": 8123.2222,
        "benchmark": "remoteSetNvRate",
        "cycles": 1986477641.0,
        "max_avg_ns": 23333.333333333332,
        "max_cycles": 7000000000.0,
        "name": "variable_rate_perf_remoteSetNvRate",
        "rate_hz": 123103,
        "threshold_pass": true,
        "timestamp": 1777009817.2545667
      }
    },
    {
      "name": "variable_rate_perf_remoteSetRate",
      "complete": true,
      "rx_errors": "n/a",
      "rate_display": "9414.131 ns/op, 106223 ops/s",
      "notes": [
        "cycles=2302158057.000",
        "threshold_pass=yes"
      ],
      "primary_metric": {
        "key": "avg_ns",
        "value": 9414.13086,
        "unit": "ns/op",
        "better": "lower",
        "display": "9414.131 ns/op"
      },
      "raw": {
        "avg_ns": 9414.13086,
        "benchmark": "remoteSetRate",
        "cycles": 2302158057.0,
        "max_avg_ns": 26666.666666666668,
        "max_cycles": 8000000000.0,
        "name": "variable_rate_perf_remoteSetRate",
        "rate_hz": 106223,
        "threshold_pass": true,
        "timestamp": 1777009816.4417272
      }
    }
  ]
}
