{
  "schema_version": 1,
  "ref_name": "ESROGUE-740",
  "ref_slug": "ESROGUE-740",
  "sha": "6341bb6417ef574e11fb1375a85d8a75cbd3d90f",
  "short_sha": "6341bb6",
  "run_id": "24703174524",
  "run_url": "https://github.com/slaclab/rogue/actions/runs/24703174524",
  "published_at": "2026-04-21T03:59:56Z",
  "benchmarks": [
    {
      "name": "fifo_perf",
      "complete": true,
      "rx_errors": 0,
      "rate_display": "31.163 MB/s",
      "notes": [
        "frames=10000/10000",
        "elapsed=3.060 s"
      ],
      "primary_metric": {
        "key": "throughput_mb_s",
        "value": 31.162542037818827,
        "unit": "MB/s",
        "better": "higher",
        "display": "31.163 MB/s"
      },
      "raw": {
        "drain_complete": true,
        "elapsed_sec": 3.060322599000017,
        "frame_size": 10000,
        "frames_received": 10000,
        "frames_sent": 10000,
        "name": "fifo_perf",
        "rx_errors": 0,
        "throughput_mb_s": 31.162542037818827,
        "timestamp": 1776743932.2376657
      }
    },
    {
      "name": "stream_bridge_perf",
      "complete": true,
      "rx_errors": 0,
      "rate_display": "32.136 MB/s",
      "notes": [
        "frames=10000/10000",
        "elapsed=2.968 s"
      ],
      "primary_metric": {
        "key": "throughput_mb_s",
        "value": 32.136225051570776,
        "unit": "MB/s",
        "better": "higher",
        "display": "32.136 MB/s"
      },
      "raw": {
        "drain_complete": true,
        "elapsed_sec": 2.967599072000013,
        "frame_size": 10000,
        "frames_received": 10000,
        "frames_sent": 10000,
        "name": "stream_bridge_perf",
        "rx_errors": 0,
        "throughput_mb_s": 32.136225051570776,
        "timestamp": 1776743935.2087789
      }
    },
    {
      "name": "udp_packetizer_perf_v1_jumbo",
      "complete": true,
      "rx_errors": 0,
      "rate_display": "27.393 MB/s",
      "notes": [
        "frames=10000/10000",
        "elapsed=3.481 s",
        "ver=1",
        "jumbo=yes"
      ],
      "primary_metric": {
        "key": "throughput_mb_s",
        "value": 27.39323331000439,
        "unit": "MB/s",
        "better": "higher",
        "display": "27.393 MB/s"
      },
      "raw": {
        "drain_complete": true,
        "elapsed_sec": 3.4814229689999934,
        "frame_size": 10000,
        "frames_received": 10000,
        "frames_sent": 10000,
        "jumbo": true,
        "name": "udp_packetizer_perf_v1_jumbo",
        "rx_errors": 0,
        "throughput_mb_s": 27.39323331000439,
        "timestamp": 1776743939.7283435,
        "version": 1
      }
    },
    {
      "name": "udp_packetizer_perf_v1_std",
      "complete": true,
      "rx_errors": 0,
      "rate_display": "23.185 MB/s",
      "notes": [
        "frames=10000/10000",
        "elapsed=4.113 s",
        "ver=1",
        "jumbo=no"
      ],
      "primary_metric": {
        "key": "throughput_mb_s",
        "value": 23.184514358874086,
        "unit": "MB/s",
        "better": "higher",
        "display": "23.185 MB/s"
      },
      "raw": {
        "drain_complete": true,
        "elapsed_sec": 4.113410794999993,
        "frame_size": 10000,
        "frames_received": 10000,
        "frames_sent": 10000,
        "jumbo": false,
        "name": "udp_packetizer_perf_v1_std",
        "rx_errors": 0,
        "throughput_mb_s": 23.184514358874086,
        "timestamp": 1776743949.3791208,
        "version": 1
      }
    },
    {
      "name": "udp_packetizer_perf_v2_jumbo",
      "complete": true,
      "rx_errors": 0,
      "rate_display": "26.982 MB/s",
      "notes": [
        "frames=10000/10000",
        "elapsed=3.535 s",
        "ver=2",
        "jumbo=yes"
      ],
      "primary_metric": {
        "key": "throughput_mb_s",
        "value": 26.981849406916016,
        "unit": "MB/s",
        "better": "higher",
        "display": "26.982 MB/s"
      },
      "raw": {
        "drain_complete": true,
        "elapsed_sec": 3.5345031470000094,
        "frame_size": 10000,
        "frames_received": 10000,
        "frames_sent": 10000,
        "jumbo": true,
        "name": "udp_packetizer_perf_v2_jumbo",
        "rx_errors": 0,
        "throughput_mb_s": 26.981849406916016,
        "timestamp": 1776743944.2641866,
        "version": 2
      }
    },
    {
      "name": "udp_packetizer_perf_v2_std",
      "complete": true,
      "rx_errors": 0,
      "rate_display": "22.217 MB/s",
      "notes": [
        "frames=10000/10000",
        "elapsed=4.293 s",
        "ver=2",
        "jumbo=no"
      ],
      "primary_metric": {
        "key": "throughput_mb_s",
        "value": 22.216672596426424,
        "unit": "MB/s",
        "better": "higher",
        "display": "22.217 MB/s"
      },
      "raw": {
        "drain_complete": true,
        "elapsed_sec": 4.292606430000006,
        "frame_size": 10000,
        "frames_received": 10000,
        "frames_sent": 10000,
        "jumbo": false,
        "name": "udp_packetizer_perf_v2_std",
        "rx_errors": 0,
        "throughput_mb_s": 22.216672596426424,
        "timestamp": 1776743954.6730454,
        "version": 2
      }
    },
    {
      "name": "variable_rate_perf_linkedGetRate",
      "complete": true,
      "rx_errors": "n/a",
      "rate_display": "8454.790 ns/op, 118276 ops/s",
      "notes": [
        "cycles=2067545151.000",
        "threshold_pass=yes"
      ],
      "primary_metric": {
        "key": "avg_ns",
        "value": 8454.78953,
        "unit": "ns/op",
        "better": "lower",
        "display": "8454.790 ns/op"
      },
      "raw": {
        "avg_ns": 8454.78953,
        "benchmark": "linkedGetRate",
        "cycles": 2067545151.0,
        "max_avg_ns": 26666.666666666668,
        "max_cycles": 8000000000.0,
        "name": "variable_rate_perf_linkedGetRate",
        "rate_hz": 118276,
        "threshold_pass": true,
        "timestamp": 1776743959.9775004
      }
    },
    {
      "name": "variable_rate_perf_linkedSetRate",
      "complete": true,
      "rx_errors": "n/a",
      "rate_display": "11863.084 ns/op, 84295 ops/s",
      "notes": [
        "cycles=2901015870.000",
        "threshold_pass=yes"
      ],
      "primary_metric": {
        "key": "avg_ns",
        "value": 11863.08431,
        "unit": "ns/op",
        "better": "lower",
        "display": "11863.084 ns/op"
      },
      "raw": {
        "avg_ns": 11863.08431,
        "benchmark": "linkedSetRate",
        "cycles": 2901015870.0,
        "max_avg_ns": 30000.0,
        "max_cycles": 9000000000.0,
        "name": "variable_rate_perf_linkedSetRate",
        "rate_hz": 84295,
        "threshold_pass": true,
        "timestamp": 1776743959.1315553
      }
    },
    {
      "name": "variable_rate_perf_localGetRate",
      "complete": true,
      "rx_errors": "n/a",
      "rate_display": "1773.574 ns/op, 563833 ops/s",
      "notes": [
        "cycles=433712647.000",
        "threshold_pass=yes"
      ],
      "primary_metric": {
        "key": "avg_ns",
        "value": 1773.57364,
        "unit": "ns/op",
        "better": "lower",
        "display": "1773.574 ns/op"
      },
      "raw": {
        "avg_ns": 1773.57364,
        "benchmark": "localGetRate",
        "cycles": 433712647.0,
        "max_avg_ns": 20000.0,
        "max_cycles": 6000000000.0,
        "name": "variable_rate_perf_localGetRate",
        "rate_hz": 563833,
        "threshold_pass": true,
        "timestamp": 1776743957.9436657
      }
    },
    {
      "name": "variable_rate_perf_localSetRate",
      "complete": true,
      "rx_errors": "n/a",
      "rate_display": "2402.872 ns/op, 416168 ops/s",
      "notes": [
        "cycles=587606922.000",
        "threshold_pass=yes"
      ],
      "primary_metric": {
        "key": "avg_ns",
        "value": 2402.87175,
        "unit": "ns/op",
        "better": "lower",
        "display": "2402.872 ns/op"
      },
      "raw": {
        "avg_ns": 2402.87175,
        "benchmark": "localSetRate",
        "cycles": 587606922.0,
        "max_avg_ns": 26666.666666666668,
        "max_cycles": 8000000000.0,
        "name": "variable_rate_perf_localSetRate",
        "rate_hz": 416168,
        "threshold_pass": true,
        "timestamp": 1776743957.7659295
      }
    },
    {
      "name": "variable_rate_perf_remoteGetRate",
      "complete": true,
      "rx_errors": "n/a",
      "rate_display": "7759.532 ns/op, 128873 ops/s",
      "notes": [
        "cycles=1897528944.000",
        "threshold_pass=yes"
      ],
      "primary_metric": {
        "key": "avg_ns",
        "value": 7759.53226,
        "unit": "ns/op",
        "better": "lower",
        "display": "7759.532 ns/op"
      },
      "raw": {
        "avg_ns": 7759.53226,
        "benchmark": "remoteGetRate",
        "cycles": 1897528944.0,
        "max_avg_ns": 20000.0,
        "max_cycles": 6000000000.0,
        "name": "variable_rate_perf_remoteGetRate",
        "rate_hz": 128873,
        "threshold_pass": true,
        "timestamp": 1776743957.5252185
      }
    },
    {
      "name": "variable_rate_perf_remoteSetNvRate",
      "complete": true,
      "rx_errors": "n/a",
      "rate_display": "9452.335 ns/op, 105793 ops/s",
      "notes": [
        "cycles=2311490010.000",
        "threshold_pass=yes"
      ],
      "primary_metric": {
        "key": "avg_ns",
        "value": 9452.33488,
        "unit": "ns/op",
        "better": "lower",
        "display": "9452.335 ns/op"
      },
      "raw": {
        "avg_ns": 9452.33488,
        "benchmark": "remoteSetNvRate",
        "cycles": 2311490010.0,
        "max_avg_ns": 23333.333333333332,
        "max_cycles": 7000000000.0,
        "name": "variable_rate_perf_remoteSetNvRate",
        "rate_hz": 105793,
        "threshold_pass": true,
        "timestamp": 1776743956.7488213
      }
    },
    {
      "name": "variable_rate_perf_remoteSetRate",
      "complete": true,
      "rx_errors": "n/a",
      "rate_display": "11197.680 ns/op, 89304 ops/s",
      "notes": [
        "cycles=2738301893.000",
        "threshold_pass=yes"
      ],
      "primary_metric": {
        "key": "avg_ns",
        "value": 11197.68001,
        "unit": "ns/op",
        "better": "lower",
        "display": "11197.680 ns/op"
      },
      "raw": {
        "avg_ns": 11197.68001,
        "benchmark": "remoteSetRate",
        "cycles": 2738301893.0,
        "max_avg_ns": 26666.666666666668,
        "max_cycles": 8000000000.0,
        "name": "variable_rate_perf_remoteSetRate",
        "rate_hz": 89304,
        "threshold_pass": true,
        "timestamp": 1776743955.803126
      }
    }
  ]
}
